cypherkit/__init__.py
cypherkit/communication.py
cypherkit/file_crypto.py
cypherkit/hashing.py
cypherkit/password.py
cypherkit/steganography.py
cypherkit-1.0.1.dist-info/METADATA
cypherkit-1.0.1.dist-info/WHEEL
cypherkit-1.0.1.dist-info/top_level.txt
cypherkit-1.0.1.dist-info/RECORD
