Metadata-Version: 2.4
Name: cypherkit
Version: 1.0.1
Summary: A basic library for cryptographic operations like hashing, encryption, and steganography
Home-page: https://github.com/fahimdidnt/cypherkit
Author: Fahim Ahmed
Author-email: fahimdidnt@gmail.com
License: MIT
Classifier: License :: OSI Approved :: MIT License
Classifier: Programming Language :: Python :: 3
Classifier: Programming Language :: Python :: 3.7
Classifier: Programming Language :: Python :: 3.8
Classifier: Programming Language :: Python :: 3.9
Requires-Dist: pycryptodome
Requires-Dist: Pillow
Dynamic: author
Dynamic: author-email
Dynamic: classifier
Dynamic: description
Dynamic: description-content-type
Dynamic: home-page
Dynamic: license
Dynamic: requires-dist
Dynamic: summary
